subpatch.py
subpatch-0.1a6.dist-info/licenses/LICENSE
subpatch-0.1a6.dist-info/licenses/LICENSE_Attribution-ShareAlike 4.0 International
subpatch-0.1a6.dist-info/licenses/LICENSE_GPLv2
subpatch-0.1a6.dist-info/METADATA
subpatch-0.1a6.dist-info/WHEEL
subpatch-0.1a6.dist-info/entry_points.txt
subpatch-0.1a6.dist-info/top_level.txt
subpatch-0.1a6.dist-info/RECORD
