Metadata-Version: 2.4
Name: subpatch
Version: 0.1a6
Summary: fearless multi repository management - stay relaxed!
Author-email: Stefan Lengfeld <stefan@lengfeld.xyz>
Maintainer-email: Stefan Lengfeld <stefan@lengfeld.xyz>
License: GPL-2.0-only
Project-URL: Homepage, https://subpatch.net
Project-URL: Repository, https://github.com/lengfeld/subpatch
Project-URL: Issues, https://github.com/lengfeld/subpatch/issues
Classifier: Development Status :: 2 - Pre-Alpha
Classifier: Intended Audience :: Developers
Classifier: Environment :: Console
Classifier: License :: OSI Approved :: GNU General Public License v2 or later (GPLv2+)
Classifier: Programming Language :: Python :: 3
Requires-Python: >=3.8
License-File: LICENSE
License-File: LICENSE_Attribution-ShareAlike 4.0 International
License-File: LICENSE_GPLv2
Dynamic: license-file
